juice_coverage_reporter/__init__.py
juice_coverage_reporter/juice_coverage_reporter_cmd.py
juice_coverage_reporter/commons/__init__.py
juice_coverage_reporter/commons/coverage_info_handler.py
juice_coverage_reporter/commons/env_variables.py
juice_coverage_reporter/commons/mission_phases_handler.py
juice_coverage_reporter/commons/my_log.py
juice_coverage_reporter/commons/rst_report.py
juice_coverage_reporter/commons/sht_rest_api.py
juice_coverage_reporter/report/__init__.py
juice_coverage_reporter/report/coverage_report.py
juice_coverage_reporter/report/plan_stats.py
juice_coverage_reporter/report/report_methods.py
juice_coverage_reporter/report/rst_report.py
juice_coverage_reporter/report/templates/custom-reference.docx
juice_coverage_reporter/report/templates/default_rst2pdf.style
test/__init__.py
test/test_rest_api.py
juice_coverage_reporter-0.0.9.dist-info/METADATA
juice_coverage_reporter-0.0.9.dist-info/WHEEL
juice_coverage_reporter-0.0.9.dist-info/entry_points.txt
juice_coverage_reporter-0.0.9.dist-info/top_level.txt
juice_coverage_reporter-0.0.9.dist-info/RECORD
